inforcehub/__init__.py
inforcehub/anonymize.py
inforcehub/colors.py
inforcehub/inforcehub.py
inforcehub-0.2.2.dist-info/AUTHORS.rst
inforcehub-0.2.2.dist-info/LICENSE.txt
inforcehub-0.2.2.dist-info/METADATA
inforcehub-0.2.2.dist-info/WHEEL
inforcehub-0.2.2.dist-info/top_level.txt
inforcehub-0.2.2.dist-info/RECORD
