Metadata-Version: 2.1
Name: inforcehub
Version: 0.2.2
Summary: Utilities for data science and customer management
Home-page: https://github.com/inforcehub/inforcehub
Author: inforcehub
Author-email: matt.gosden@inforcehub.com
License: GNU
Keywords: inforcehub
Platform: UNKNOWN
Classifier: Development Status :: 2 - Pre-Alpha
Classifier: Intended Audience :: Financial and Insurance Industry
Classifier: License :: OSI Approved :: GNU General Public License v3 (GPLv3)
Classifier: Natural Language :: English
Classifier: Programming Language :: Python :: 3 :: Only
Classifier: Programming Language :: Python :: 3.5
Classifier: Programming Language :: Python :: 3.6
Classifier: Programming Language :: Python :: 3.7
Classifier: Operating System :: OS Independent
Classifier: Topic :: Office/Business :: Financial
Classifier: Topic :: Software Development :: Libraries :: Python Modules
Requires-Dist: pandas
Requires-Dist: bcrypt
